mofid_normalizer/__init__.py
mofid_normalizer/abbreviation.py
mofid_normalizer/add_vocab_word.py
mofid_normalizer/affix_norm.py
mofid_normalizer/charnormalizer.py
mofid_normalizer/chunker.py
mofid_normalizer/data_helper.py
mofid_normalizer/date2string.py
mofid_normalizer/dependency.py
mofid_normalizer/example.py
mofid_normalizer/mapping_words.py
mofid_normalizer/normalizer.py
mofid_normalizer/num2string.py
mofid_normalizer/postagger.py
mofid_normalizer/punctuation_remover.py
mofid_normalizer/spacy_loader.py
mofid_normalizer/spell_checker.py
mofid_normalizer/stemmer.py
mofid_normalizer/time2string.py
mofid_normalizer/token_merger.py
mofid_normalizer/tokenizer.py
mofid_normalizer/version.py
mofid_normalizer/config/affix.json
mofid_normalizer/config/character_mappings.json
mofid_normalizer/config/word_mappings.json
mofid_normalizer/resource/normalizer/Dic1_new.txt
mofid_normalizer/resource/normalizer/Dic2_new.txt
mofid_normalizer/resource/normalizer/Dic3_new.txt
mofid_normalizer/resource/stemmer/mokasar.txt
mofid_normalizer/resource/stemmer/original_parsivar_stem_lex.pckl
mofid_normalizer/resource/stemmer/original_parsivar_stem_lex2.pckl
mofid_normalizer/resource/stemmer/pasvand.txt
mofid_normalizer/resource/stemmer/pishvand.txt
mofid_normalizer/resource/stemmer/stem_irregularNounDict.pckl
mofid_normalizer/resource/stemmer/stem_lex.pckl
mofid_normalizer/resource/stemmer/stem_verbMap.pckl
mofid_normalizer/resource/stemmer/verbStemDict.pckl
mofid_normalizer/resource/stemmer/verb_tense.txt
mofid_normalizer/resource/stemmer/verb_tenses.json
mofid_normalizer-1.0.83.dist-info/METADATA
mofid_normalizer-1.0.83.dist-info/WHEEL
mofid_normalizer-1.0.83.dist-info/top_level.txt
mofid_normalizer-1.0.83.dist-info/RECORD
