Metadata-Version: 2.1
Name: mofid-normalizer
Version: 1.0.83
Summary: first version of Mofid Normalizer
Author: ali96ebrahimi@gmail.com
License: MIT
Platform: UNKNOWN
Requires-Dist: nltk
Requires-Dist: num2fawords
Requires-Dist: spacy
Requires-Dist: googledrivedownloader
